make_a_gif.py
make_a_gif-0.2.0.dist-info/licenses/LICENSE
make_a_gif-0.2.0.dist-info/METADATA
make_a_gif-0.2.0.dist-info/WHEEL
make_a_gif-0.2.0.dist-info/top_level.txt
make_a_gif-0.2.0.dist-info/RECORD
