Metadata-Version: 2.4
Name: make-a-gif
Version: 0.2.0
Summary: Make gifs in python.
Author-email: John Gardner <gardner.john97+dphil@gmail.com>
License: MIT License
Project-URL: Homepage, https://github.com/jla-gardner/make-a-gif
Keywords: gifs,plots,images,animation
Classifier: License :: OSI Approved :: MIT License
Classifier: Programming Language :: Python
Classifier: Programming Language :: Python :: 3
Requires-Python: >=3.11
License-File: LICENSE
Requires-Dist: ipython>=9.0
Requires-Dist: matplotlib>=3.10.0
Requires-Dist: Pillow>=11.3.0
Dynamic: license-file
